Metadata-Version: 2.4
Name: pps3transfer
Version: 0.12.0
Summary: An Amazon S3 Transfer Manager
Home-page: https://github.com/boto/s3transfer
Author: Amazon Web Services
Author-email: kyknapp1@gmail.com
License: Apache License 2.0
Classifier: Development Status :: 3 - Alpha
Classifier: Intended Audience :: Developers
Classifier: Natural Language :: English
Classifier: License :: OSI Approved :: Apache Software License
Classifier: Programming Language :: Python
Classifier: Programming Language :: Python :: 3
Classifier: Programming Language :: Python :: 3 :: Only
Classifier: Programming Language :: Python :: 3.9
Classifier: Programming Language :: Python :: 3.10
Classifier: Programming Language :: Python :: 3.11
Classifier: Programming Language :: Python :: 3.12
Classifier: Programming Language :: Python :: 3.13
Requires-Python: >= 3.9
License-File: LICENSE.txt
License-File: NOTICE.txt
Requires-Dist: botocore<2.0a.0,>=1.37.4
Provides-Extra: crt
Requires-Dist: botocore[crt]<2.0a.0,>=1.37.4; extra == "crt"
Dynamic: author
Dynamic: author-email
Dynamic: classifier
Dynamic: description
Dynamic: home-page
Dynamic: license
Dynamic: license-file
Dynamic: provides-extra
Dynamic: requires-dist
Dynamic: requires-python
Dynamic: summary
